CHANGELOG.rst
LICENSE.txt
MANIFEST.in
README.rst
pyproject.toml
setup.cfg
docplex/__init__.py
docplex/version.py
docplex.egg-info/PKG-INFO
docplex.egg-info/SOURCES.txt
docplex.egg-info/dependency_links.txt
docplex.egg-info/requires.txt
docplex.egg-info/top_level.txt
docplex/cp/__init__.py
docplex/cp/blackbox.py
docplex/cp/catalog.py
docplex/cp/check_list.py
docplex/cp/config.py
docplex/cp/expression.py
docplex/cp/function.py
docplex/cp/model.py
docplex/cp/modeler.py
docplex/cp/parameters.py
docplex/cp/solution.py
docplex/cp/tokenizer.py
docplex/cp/utils.py
docplex/cp/utils_visu.py
docplex/cp/cpo/__init__.py
docplex/cp/cpo/cpo_compiler.py
docplex/cp/cpo/cpo_parser.py
docplex/cp/cpo/cpo_tokenizer.py
docplex/cp/fzn/__init__.py
docplex/cp/fzn/fzn_parser.py
docplex/cp/fzn/fzn_tokenizer.py
docplex/cp/lp/__init__.py
docplex/cp/lp/lp_parser.py
docplex/cp/lp/lp_tokenizer.py
docplex/cp/solver/__init__.py
docplex/cp/solver/cpo_callback.py
docplex/cp/solver/environment_client.py
docplex/cp/solver/solver.py
docplex/cp/solver/solver_lib.py
docplex/cp/solver/solver_listener.py
docplex/cp/solver/solver_local.py
docplex/cp/solver/solver_simulator.py
docplex/mp/__init__.py
docplex/mp/advmodel.py
docplex/mp/aggregator.py
docplex/mp/anno.py
docplex/mp/basic.py
docplex/mp/check_list.py
docplex/mp/conflict_refiner.py
docplex/mp/constants.py
docplex/mp/constr.py
docplex/mp/context.py
docplex/mp/cplex_adapter.py
docplex/mp/cplex_engine.py
docplex/mp/ds_utils.py
docplex/mp/dvar.py
docplex/mp/engine.py
docplex/mp/engine_factory.py
docplex/mp/environment.py
docplex/mp/error_handler.py
docplex/mp/format.py
docplex/mp/functional.py
docplex/mp/kpi.py
docplex/mp/linear.py
docplex/mp/lp_printer.py
docplex/mp/mfactory.py
docplex/mp/model.py
docplex/mp/model_reader.py
docplex/mp/model_stats.py
docplex/mp/mprinter.py
docplex/mp/numutils.py
docplex/mp/operand.py
docplex/mp/ppretty.py
docplex/mp/priority.py
docplex/mp/progress.py
docplex/mp/publish.py
docplex/mp/pwl.py
docplex/mp/qprogress.py
docplex/mp/quad.py
docplex/mp/quadfact.py
docplex/mp/relax_linear.py
docplex/mp/relaxer.py
docplex/mp/sdetails.py
docplex/mp/sol_xml_reader.py
