Metadata-Version: 2.1
Name: docplex
Version: 2.27.239
Summary: The IBM Decision Optimization CPLEX Modeling for Python
Home-page: https://www.ibm.com/cloud/decision-optimization-for-watson-studio
Author: The IBM Decision Optimization on Cloud team
License: Apache 2.0
Keywords: optimization,cplex,cpo
Classifier: Development Status :: 5 - Production/Stable
Classifier: Intended Audience :: Developers
Classifier: Intended Audience :: Information Technology
Classifier: Intended Audience :: Science/Research
Classifier: Operating System :: Unix
Classifier: Operating System :: MacOS
Classifier: Operating System :: Microsoft
Classifier: Operating System :: OS Independent
Classifier: Topic :: Scientific/Engineering
Classifier: Topic :: Scientific/Engineering :: Mathematics
Classifier: Topic :: Software Development :: Libraries
Classifier: Topic :: System
Classifier: Topic :: Other/Nonlisted Topic
Classifier: License :: OSI Approved :: Apache Software License
Classifier: Programming Language :: Python :: 3
License-File: LICENSE.txt
Requires-Dist: six
